LICENSE.txt
README.md
setup.cfg
setup.py
dolibarrpy/Dolibarrpy.py
dolibarrpy/__init__.py
dolibarrpy/dolibarrpy.py
dolibarrpy.egg-info/PKG-INFO
dolibarrpy.egg-info/SOURCES.txt
dolibarrpy.egg-info/dependency_links.txt
dolibarrpy.egg-info/top_level.txt